safe_llm_parser/__init__.py
safe_llm_parser/models.py
safe_llm_parser/parser.py
safe_llm_parser/prompts.py
safe_llm_parser/safe_parser.py
safe_llm_parser-0.1.0.dist-info/METADATA
safe_llm_parser-0.1.0.dist-info/WHEEL
safe_llm_parser-0.1.0.dist-info/RECORD
