Metadata-Version: 2.1
Name: safe_llm_parser
Version: 0.1.0
Summary: Reliable way to parse LLM outputs
License: MIT
Author: wmpons.pro
Author-email: wmpons.pro@gmail.com
Requires-Python: >=3.8,<4.0
Classifier: License :: OSI Approved :: MIT License
Classifier: Programming Language :: Python :: 3
Classifier: Programming Language :: Python :: 3.8
Classifier: Programming Language :: Python :: 3.9
Classifier: Programming Language :: Python :: 3.10
Classifier: Programming Language :: Python :: 3.11
Classifier: Programming Language :: Python :: 3.12
Requires-Dist: beautifulsoup4 (>=4.12.3,<5.0.0)
Requires-Dist: lxml (>=5.3.0,<6.0.0)
Requires-Dist: pydantic (>=2.9.1,<3.0.0)
Requires-Dist: types-beautifulsoup4 (>=4.12.0.20240907,<5.0.0.0)
